datahorders_cdn/__init__.py
datahorders_cdn/client.py
datahorders_cdn/exceptions.py
datahorders_cdn/models.py
datahorders_cdn/py.typed
datahorders_cdn/resources/__init__.py
datahorders_cdn/resources/analytics.py
datahorders_cdn/resources/base.py
datahorders_cdn/resources/certificates.py
datahorders_cdn/resources/domains.py
datahorders_cdn/resources/health_checks.py
datahorders_cdn/resources/upstream_servers.py
datahorders_cdn/resources/waf.py
datahorders_cdn/resources/zones.py
datahorders_cdn-1.0.0.dist-info/METADATA
datahorders_cdn-1.0.0.dist-info/WHEEL
datahorders_cdn-1.0.0.dist-info/licenses/LICENSE
datahorders_cdn-1.0.0.dist-info/RECORD
