Metadata-Version: 2.4
Name: datahorders-cdn
Version: 1.0.0
Summary: Python SDK for the DataHorders CDN API
Project-URL: Homepage, https://datahorders.org
Project-URL: Documentation, https://wiki.datahorders.org/api
Project-URL: Repository, https://github.com/datahorders/cdn-python-sdk
Project-URL: Changelog, https://github.com/datahorders/cdn-python-sdk/blob/main/CHANGELOG.md
Project-URL: Issues, https://github.com/datahorders/cdn-python-sdk/issues
Author-email: DataHorders <support@datahorders.org>
License-Expression: MIT
License-File: LICENSE
Keywords: api,cdn,datahorders,reverse-proxy,sdk,ssl,waf
Classifier: Development Status :: 5 - Production/Stable
Classifier: Intended Audience :: Developers
Classifier: License :: OSI Approved :: MIT License
Classifier: Operating System :: OS Independent
Classifier: Programming Language :: Python :: 3
Classifier: Programming Language :: Python :: 3.9
Classifier: Programming Language :: Python :: 3.10
Classifier: Programming Language :: Python :: 3.11
Classifier: Programming Language :: Python :: 3.12
Classifier: Programming Language :: Python :: 3.13
Classifier: Topic :: Internet :: WWW/HTTP
Classifier: Topic :: Software Development :: Libraries :: Python Modules
Classifier: Typing :: Typed
Requires-Python: >=3.9
Requires-Dist: httpx>=0.25.0
Requires-Dist: pydantic>=2.0.0
Provides-Extra: dev
Requires-Dist: black>=23.0.0; extra == 'dev'
Requires-Dist: mypy>=1.0.0; extra == 'dev'
Requires-Dist: pytest-asyncio>=0.21.0; extra == 'dev'
Requires-Dist: pytest-cov>=4.0.0; extra == 'dev'
Requires-Dist: pytest>=7.0.0; extra == 'dev'
Requires-Dist: respx>=0.20.0; extra == 'dev'
Requires-Dist: ruff>=0.1.0; extra == 'dev'
